aces/__init__.py
aces/config.py
aces/data_processor.py
aces/ee_utils.py
aces/metrics.py
aces/model_builder.py
aces/model_trainer.py
aces/remote_sensing.py
aces/utils.py
examples/__init__.py
examples/count_sample_size.py
examples/run_model_example.py
servir_aces-2024.1.1.dist-info/LICENSE
servir_aces-2024.1.1.dist-info/METADATA
servir_aces-2024.1.1.dist-info/WHEEL
servir_aces-2024.1.1.dist-info/top_level.txt
servir_aces-2024.1.1.dist-info/RECORD
