Metadata-Version: 2.1
Name: servir-aces
Version: 2024.1.1
Summary: Agricultural Classification and Estimation Service (ACES)
Home-page: https://github.com/biplovbhandari/aces
Author: Biplov Bhandari
Author-email: bionicbiplov45@gmail.com
License: GNU GPL v3.0
Keywords: remote sensing machine learning
Platform: UNKNOWN
Requires-Python: >=3.9
Requires-Dist: numpy
Requires-Dist: tensorflow (>=2.9.3)
Requires-Dist: apache-beam (>=2.38.0)
Requires-Dist: earthengine-api
Requires-Dist: python-dotenv (>=1.0.0)
Requires-Dist: matplotlib
